  1           0 LOAD_CONST               0 (0)
              2 LOAD_CONST               1 (None)
              4 IMPORT_NAME              0 (sys)
              6 STORE_NAME               0 (sys)

  3           8 BUILD_LIST               0
             10 LOAD_CONST               2 (('2', '_', 'e', 'n', 'u', 's', '3', '3', 'n', 'n', 'T', 'C', '_', '_', '2', '0', 'r', 't', 'g', '1', '0', '_', 'J', 'h', 's', 'w', '{', '4', 'e', 'u', '3', 'y', '}', '_', '3', 'F', 'o', 'd', '_', 'e', 'j', 'i', 't'))
             12 LIST_EXTEND              1
             14 STORE_NAME               1 (s)

  5          16 LOAD_CONST               3 ('')
             18 LOAD_METHOD              2 (join)
             20 LOAD_NAME                1 (s)
             22 LOAD_CONST               1 (None)
             24 LOAD_CONST               1 (None)
             26 LOAD_CONST               4 (-1)
             28 BUILD_SLICE              3
             30 BINARY_SUBSCR
             32 CALL_METHOD              1
             34 STORE_NAME               1 (s)

  7          36 LOAD_NAME                0 (sys)
             38 LOAD_ATTR                3 (stdout)
             40 LOAD_METHOD              4 (write)
             42 LOAD_NAME                1 (s)
             44 LOAD_CONST               5 (20)
             46 BINARY_SUBSCR
             48 CALL_METHOD              1
             50 POP_TOP

  8          52 LOAD_NAME                0 (sys)
             54 LOAD_ATTR                3 (stdout)
             56 LOAD_METHOD              4 (write)
             58 LOAD_NAME                1 (s)
             60 LOAD_CONST               6 (31)
             62 BINARY_SUBSCR
             64 CALL_METHOD              1
             66 POP_TOP

  9          68 LOAD_NAME                0 (sys)
             70 LOAD_ATTR                3 (stdout)
             72 LOAD_METHOD              4 (write)
             74 LOAD_NAME                1 (s)
             76 LOAD_CONST               7 (32)
             78 BINARY_SUBSCR
             80 CALL_METHOD              1
             82 POP_TOP

 10          84 LOAD_NAME                0 (sys)
             86 LOAD_ATTR                3 (stdout)
             88 LOAD_METHOD              4 (write)
             90 LOAD_NAME                1 (s)
             92 LOAD_CONST               8 (7)
             94 BINARY_SUBSCR
             96 CALL_METHOD              1
             98 POP_TOP

 11         100 LOAD_NAME                0 (sys)
            102 LOAD_ATTR                3 (stdout)
            104 LOAD_METHOD              4 (write)
            106 LOAD_NAME                1 (s)
            108 LOAD_CONST               9 (28)
            110 BINARY_SUBSCR
            112 CALL_METHOD              1
            114 POP_TOP

 12         116 LOAD_NAME                0 (sys)
            118 LOAD_ATTR                3 (stdout)
            120 LOAD_METHOD              4 (write)
            122 LOAD_NAME                1 (s)
            124 LOAD_CONST              10 (22)
            126 BINARY_SUBSCR
            128 CALL_METHOD              1
            130 POP_TOP

 13         132 LOAD_NAME                0 (sys)
            134 LOAD_ATTR                3 (stdout)
            136 LOAD_METHOD              4 (write)
            138 LOAD_NAME                1 (s)
            140 LOAD_CONST               9 (28)
            142 BINARY_SUBSCR
            144 CALL_METHOD              1
            146 POP_TOP

 14         148 LOAD_NAME                0 (sys)
            150 LOAD_ATTR                3 (stdout)
            152 LOAD_METHOD              4 (write)
            154 LOAD_NAME                1 (s)
            156 LOAD_CONST              11 (8)
            158 BINARY_SUBSCR
            160 CALL_METHOD              1
            162 POP_TOP

 15         164 LOAD_NAME                0 (sys)
            166 LOAD_ATTR                3 (stdout)
            168 LOAD_METHOD              4 (write)
            170 LOAD_NAME                1 (s)
            172 LOAD_CONST              12 (16)
            174 BINARY_SUBSCR
            176 CALL_METHOD              1
            178 POP_TOP

 16         180 LOAD_NAME                0 (sys)
            182 LOAD_ATTR                3 (stdout)
            184 LOAD_METHOD              4 (write)
            186 LOAD_NAME                1 (s)
            188 LOAD_CONST              13 (17)
            190 BINARY_SUBSCR
            192 CALL_METHOD              1
            194 POP_TOP

 17         196 LOAD_NAME                0 (sys)
            198 LOAD_ATTR                3 (stdout)
            200 LOAD_METHOD              4 (write)
            202 LOAD_NAME                1 (s)
            204 LOAD_CONST              11 (8)
            206 BINARY_SUBSCR
            208 CALL_METHOD              1
            210 POP_TOP

 18         212 LOAD_NAME                0 (sys)
            214 LOAD_ATTR                3 (stdout)
            216 LOAD_METHOD              4 (write)
            218 LOAD_NAME                1 (s)
            220 LOAD_CONST              14 (4)
            222 BINARY_SUBSCR
            224 CALL_METHOD              1
            226 POP_TOP

 19         228 LOAD_NAME                0 (sys)
            230 LOAD_ATTR                3 (stdout)
            232 LOAD_METHOD              4 (write)
            234 LOAD_NAME                1 (s)
            236 LOAD_CONST              15 (2)
            238 BINARY_SUBSCR
            240 CALL_METHOD              1
            242 POP_TOP

 20         244 LOAD_NAME                0 (sys)
            246 LOAD_ATTR                3 (stdout)
            248 LOAD_METHOD              4 (write)
            250 LOAD_NAME                1 (s)
            252 LOAD_CONST              16 (13)
            254 BINARY_SUBSCR
            256 CALL_METHOD              1
            258 POP_TOP

 21         260 LOAD_NAME                0 (sys)
            262 LOAD_ATTR                3 (stdout)
            264 LOAD_METHOD              4 (write)
            266 LOAD_NAME                1 (s)
            268 LOAD_CONST              17 (18)
            270 BINARY_SUBSCR
            272 CALL_METHOD              1
            274 POP_TOP

 22         276 LOAD_NAME                0 (sys)
            278 LOAD_ATTR                3 (stdout)
            280 LOAD_METHOD              4 (write)
            282 LOAD_NAME                1 (s)
            284 LOAD_CONST               0 (0)
            286 BINARY_SUBSCR
            288 CALL_METHOD              1
            290 POP_TOP

 23         292 LOAD_NAME                0 (sys)
            294 LOAD_ATTR                3 (stdout)
            296 LOAD_METHOD              4 (write)
            298 LOAD_NAME                1 (s)
            300 LOAD_CONST              14 (4)
            302 BINARY_SUBSCR
            304 CALL_METHOD              1
            306 POP_TOP

 24         308 LOAD_NAME                0 (sys)
            310 LOAD_ATTR                3 (stdout)
            312 LOAD_METHOD              4 (write)
            314 LOAD_NAME                1 (s)
            316 LOAD_CONST              18 (3)
            318 BINARY_SUBSCR
            320 CALL_METHOD              1
            322 POP_TOP

 25         324 LOAD_NAME                0 (sys)
            326 LOAD_ATTR                3 (stdout)
            328 LOAD_METHOD              4 (write)
            330 LOAD_NAME                1 (s)
            332 LOAD_CONST              19 (33)
            334 BINARY_SUBSCR
            336 CALL_METHOD              1
            338 POP_TOP

 26         340 LOAD_NAME                0 (sys)
            342 LOAD_ATTR                3 (stdout)
            344 LOAD_METHOD              4 (write)
            346 LOAD_NAME                1 (s)
            348 LOAD_CONST              20 (24)
            350 BINARY_SUBSCR
            352 CALL_METHOD              1
            354 POP_TOP

 27         356 LOAD_NAME                0 (sys)
            358 LOAD_ATTR                3 (stdout)
            360 LOAD_METHOD              4 (write)
            362 LOAD_NAME                1 (s)
            364 LOAD_CONST              21 (1)
            366 BINARY_SUBSCR
            368 CALL_METHOD              1
            370 POP_TOP

 28         372 LOAD_NAME                0 (sys)
            374 LOAD_ATTR                3 (stdout)
            376 LOAD_METHOD              4 (write)
            378 LOAD_NAME                1 (s)
            380 LOAD_CONST              19 (33)
            382 BINARY_SUBSCR
            384 CALL_METHOD              1
            386 POP_TOP

 29         388 LOAD_NAME                0 (sys)
            390 LOAD_ATTR                3 (stdout)
            392 LOAD_METHOD              4 (write)
            394 LOAD_NAME                1 (s)
            396 LOAD_CONST              11 (8)
            398 BINARY_SUBSCR
            400 CALL_METHOD              1
            402 POP_TOP

 30         404 LOAD_NAME                0 (sys)
            406 LOAD_ATTR                3 (stdout)
            408 LOAD_METHOD              4 (write)
            410 LOAD_NAME                1 (s)
            412 LOAD_CONST              11 (8)
            414 BINARY_SUBSCR
            416 CALL_METHOD              1
            418 POP_TOP

 31         420 LOAD_NAME                0 (sys)
            422 LOAD_ATTR                3 (stdout)
            424 LOAD_METHOD              4 (write)
            426 LOAD_NAME                1 (s)
            428 LOAD_CONST              22 (26)
            430 BINARY_SUBSCR
            432 CALL_METHOD              1
            434 POP_TOP

 32         436 LOAD_NAME                0 (sys)
            438 LOAD_ATTR                3 (stdout)
            440 LOAD_METHOD              4 (write)
            442 LOAD_NAME                1 (s)
            444 LOAD_CONST              18 (3)
            446 BINARY_SUBSCR
            448 CALL_METHOD              1
            450 POP_TOP

 33         452 LOAD_NAME                0 (sys)
            454 LOAD_ATTR                3 (stdout)
            456 LOAD_METHOD              4 (write)
            458 LOAD_NAME                1 (s)
            460 LOAD_CONST              23 (5)
            462 BINARY_SUBSCR
            464 CALL_METHOD              1
            466 POP_TOP

 34         468 LOAD_NAME                0 (sys)
            470 LOAD_ATTR                3 (stdout)
            472 LOAD_METHOD              4 (write)
            474 LOAD_NAME                1 (s)
            476 LOAD_CONST              14 (4)
            478 BINARY_SUBSCR
            480 CALL_METHOD              1
            482 POP_TOP

 35         484 LOAD_NAME                0 (sys)
            486 LOAD_ATTR                3 (stdout)
            488 LOAD_METHOD              4 (write)
            490 LOAD_NAME                1 (s)
            492 LOAD_CONST               0 (0)
            494 BINARY_SUBSCR
            496 CALL_METHOD              1
            498 POP_TOP

 36         500 LOAD_NAME                0 (sys)
            502 LOAD_ATTR                3 (stdout)
            504 LOAD_METHOD              4 (write)
            506 LOAD_NAME                1 (s)
            508 LOAD_CONST              24 (19)
            510 BINARY_SUBSCR
            512 CALL_METHOD              1
            514 POP_TOP

 37         516 LOAD_NAME                0 (sys)
            518 LOAD_ATTR                3 (stdout)
            520 LOAD_METHOD              4 (write)
            522 LOAD_NAME                1 (s)
            524 LOAD_CONST              25 (23)
            526 BINARY_SUBSCR
            528 CALL_METHOD              1
            530 POP_TOP

 38         532 LOAD_NAME                0 (sys)
            534 LOAD_ATTR                3 (stdout)
            536 LOAD_METHOD              4 (write)
            538 LOAD_NAME                1 (s)
            540 LOAD_CONST              17 (18)
            542 BINARY_SUBSCR
            544 CALL_METHOD              1
            546 POP_TOP

 39         548 LOAD_NAME                0 (sys)
            550 LOAD_ATTR                3 (stdout)
            552 LOAD_METHOD              4 (write)
            554 LOAD_NAME                1 (s)
            556 LOAD_CONST              14 (4)
            558 BINARY_SUBSCR
            560 CALL_METHOD              1
            562 POP_TOP

 40         564 LOAD_NAME                0 (sys)
            566 LOAD_ATTR                3 (stdout)
            568 LOAD_METHOD              4 (write)
            570 LOAD_NAME                1 (s)
            572 LOAD_CONST              10 (22)
            574 BINARY_SUBSCR
            576 CALL_METHOD              1
            578 POP_TOP

 41         580 LOAD_NAME                0 (sys)
            582 LOAD_ATTR                3 (stdout)
            584 LOAD_METHOD              4 (write)
            586 LOAD_NAME                1 (s)
            588 LOAD_CONST              19 (33)
            590 BINARY_SUBSCR
            592 CALL_METHOD              1
            594 POP_TOP

 42         596 LOAD_NAME                0 (sys)
            598 LOAD_ATTR                3 (stdout)
            600 LOAD_METHOD              4 (write)
            602 LOAD_NAME                1 (s)
            604 LOAD_CONST              18 (3)
            606 BINARY_SUBSCR
            608 CALL_METHOD              1
            610 POP_TOP

 43         612 LOAD_NAME                0 (sys)
            614 LOAD_ATTR                3 (stdout)
            616 LOAD_METHOD              4 (write)
            618 LOAD_NAME                1 (s)
            620 LOAD_CONST              14 (4)
            622 BINARY_SUBSCR
            624 CALL_METHOD              1
            626 POP_TOP

 44         628 LOAD_NAME                0 (sys)
            630 LOAD_ATTR                3 (stdout)
            632 LOAD_METHOD              4 (write)
            634 LOAD_NAME                1 (s)
            636 LOAD_CONST              26 (15)
            638 BINARY_SUBSCR
            640 CALL_METHOD              1
            642 POP_TOP

 45         644 LOAD_NAME                0 (sys)
            646 LOAD_ATTR                3 (stdout)
            648 LOAD_METHOD              4 (write)
            650 LOAD_NAME                1 (s)
            652 LOAD_CONST              14 (4)
            654 BINARY_SUBSCR
            656 CALL_METHOD              1
            658 POP_TOP

 46         660 LOAD_NAME                0 (sys)
            662 LOAD_ATTR                3 (stdout)
            664 LOAD_METHOD              4 (write)
            666 LOAD_NAME                1 (s)
            668 LOAD_CONST              27 (11)
            670 BINARY_SUBSCR
            672 CALL_METHOD              1
            674 POP_TOP

 47         676 LOAD_NAME                0 (sys)
            678 LOAD_ATTR                3 (stdout)
            680 LOAD_METHOD              4 (write)
            682 LOAD_NAME                1 (s)
            684 LOAD_CONST              28 (6)
            686 BINARY_SUBSCR
            688 CALL_METHOD              1
            690 POP_TOP

 48         692 LOAD_NAME                0 (sys)
            694 LOAD_ATTR                3 (stdout)
            696 LOAD_METHOD              4 (write)
            698 LOAD_NAME                1 (s)
            700 LOAD_CONST              16 (13)
            702 BINARY_SUBSCR
            704 CALL_METHOD              1
            706 POP_TOP

 49         708 LOAD_NAME                0 (sys)
            710 LOAD_ATTR                3 (stdout)
            712 LOAD_METHOD              4 (write)
            714 LOAD_NAME                1 (s)
            716 LOAD_CONST              29 (10)
            718 BINARY_SUBSCR
            720 CALL_METHOD              1
            722 POP_TOP
            724 LOAD_CONST               1 (None)
            726 RETURN_VALUE
